component_vis/__init__.py
component_vis/_module_utils.py
component_vis/_xarray_wrapper.py
component_vis/conftest.py
component_vis/data.py
component_vis/factor_tools.py
component_vis/model_evaluation.py
component_vis/multimodel_evaluation.py
component_vis/outliers.py
component_vis/postprocessing.py
component_vis/utils.py
component_vis/visualisation.py
component_vis/datasets/oslo_bike.nc4
component_vis/datasets/downloads/aminoacids.nc4
ComponentVis-0.0.2.dist-info/LICENSE
ComponentVis-0.0.2.dist-info/METADATA
ComponentVis-0.0.2.dist-info/WHEEL
ComponentVis-0.0.2.dist-info/top_level.txt
ComponentVis-0.0.2.dist-info/RECORD
