Metadata-Version: 2.1
Name: ComponentVis
Version: 0.0.2
Summary: Package to visualise component-based decomposition models such as PCA and PARAFAC
Home-page: https://github.com/marieroald/component-vis
Author: Marie Roald & Yngve Mardal Moe
Author-email: roald.marie@gmail.com
License: "MIT license",
Platform: UNKNOWN
Classifier: Development Status :: 2 - Pre-Alpha
Classifier: Intended Audience :: Developers
Classifier: License :: OSI Approved :: MIT License
Classifier: Natural Language :: English
Classifier: Programming Language :: Python :: 3.7
Classifier: Programming Language :: Python :: 3.8
Classifier: Programming Language :: Python :: 3.9
Requires-Dist: numpy
Requires-Dist: scipy
Requires-Dist: matplotlib
Requires-Dist: pandas (>=1.1.0)
Requires-Dist: xarray
Requires-Dist: statsmodels
Requires-Dist: plotly (>=4.12)
Provides-Extra: all
Requires-Dist: pingouin ; extra == 'all'
Provides-Extra: devel
Requires-Dist: flake8 ; extra == 'devel'
Requires-Dist: isort ; extra == 'devel'
Requires-Dist: black ; extra == 'devel'
Requires-Dist: bump2version ; extra == 'devel'
Provides-Extra: docs
Requires-Dist: sphinx ; extra == 'docs'
Requires-Dist: sphinx-gallery ; extra == 'docs'
Requires-Dist: sphinxcontrib-bibtex ; extra == 'docs'
Requires-Dist: numpydoc ; extra == 'docs'
Requires-Dist: sphinx-rtd-theme ; extra == 'docs'
Requires-Dist: tensorly ; extra == 'docs'
Provides-Extra: test
Requires-Dist: pytest ; extra == 'test'
Requires-Dist: pytest-randomly ; extra == 'test'
Requires-Dist: pytest-cov ; extra == 'test'
Requires-Dist: coverage ; extra == 'test'
Requires-Dist: tensorly ; extra == 'test'
